{"name":"G","directed":true,"strict":false,"_draw_":[{"op":"c","grad":"none","color":"#fffffe00"},{"op":"C","grad":"none","color":"#ffffff"},{"op":"P","points":[[0,0],[0,828],[260,828],[260,0]]}],"bb":"0,0,260,828","splines":"ortho","xdotversion":"1.7","_subgraph_cnt":0,"objects":[{"_gvid":0,"name":"cpsc410_ctrl_alt_elite/src/GifsCollages/GifCreator.java","_draw_":[{"op":"c","grad":"none","color":"#000000"},{"op":"e","rect":[171,810,7,18]}],"_ldraw_":[{"op":"F","size":14,"face":"Times-Roman"},{"op":"c","grad":"none","color":"#000000"},{"op":"T","pt":[171,805.8],"align":"c","width":311.41,"text":"cpsc410_ctrl_alt_elite/src/GifsCollages/GifCreator.java"}],"fixedsize":"true","height":"0.5","label":"\\N","pos":"171,810","width":"0.19444","contributors":["Ben"]},{"_gvid":1,"name":"cpsc410_ctrl_alt_elite/src/ast/COLLAGE.java","_draw_":[{"op":"c","grad":"none","color":"#000000"},{"op":"e","rect":[41,522,7,18]}],"_ldraw_":[{"op":"F","size":14,"face":"Times-Roman"},{"op":"c","grad":"none","color":"#000000"},{"op":"T","pt":[41,517.8],"align":"c","width":259.31,"text":"cpsc410_ctrl_alt_elite/src/ast/COLLAGE.java"}],"fixedsize":"true","height":"0.5","label":"\\N","pos":"41,522","width":"0.19444","contributors":["q6y0b","Ben","Cyrielle","Ceylin"]},{"_gvid":2,"name":"cpsc410_ctrl_alt_elite/src/ast/COPY.java","_draw_":[{"op":"c","grad":"none","color":"#000000"},{"op":"e","rect":[68,234,7,18]}],"_ldraw_":[{"op":"F","size":14,"face":"Times-Roman"},{"op":"c","grad":"none","color":"#000000"},{"op":"T","pt":[68,229.8],"align":"c","width":229.52,"text":"cpsc410_ctrl_alt_elite/src/ast/COPY.java"}],"fixedsize":"true","height":"0.5","label":"\\N","pos":"68,234","width":"0.19444","contributors":["Ceylin"]},{"_gvid":3,"name":"cpsc410_ctrl_alt_elite/src/ast/FILTER.java","_draw_":[{"op":"c","grad":"none","color":"#000000"},{"op":"e","rect":[188,666,7,18]}],"_ldraw_":[{"op":"F","size":14,"face":"Times-Roman"},{"op":"c","grad":"none","color":"#000000"},{"op":"T","pt":[188,661.8],"align":"c","width":240.14,"text":"cpsc410_ctrl_alt_elite/src/ast/FILTER.java"}],"fixedsize":"true","height":"0.5","label":"\\N","pos":"188,666","width":"0.19444","contributors":["Ben","Cyrielle","Ceylin"]},{"_gvid":4,"name":"cpsc410_ctrl_alt_elite/src/ast/GIF.java","_draw_":[{"op":"c","grad":"none","color":"#000000"},{"op":"e","rect":[85,450,7,18]}],"_ldraw_":[{"op":"F","size":14,"face":"Times-Roman"},{"op":"c","grad":"none","color":"#000000"},{"op":"T","pt":[85,445.8],"align":"c","width":215.43,"text":"cpsc410_ctrl_alt_elite/src/ast/GIF.java"}],"fixedsize":"true","height":"0.5","label":"\\N","pos":"85,450","width":"0.19444","contributors":["Cyrielle","Ben","q6y0b","Ceylin"]},{"_gvid":5,"name":"cpsc410_ctrl_alt_elite/src/ast/LOAD.java","_draw_":[{"op":"c","grad":"none","color":"#000000"},{"op":"e","rect":[188,306,7,18]}],"_ldraw_":[{"op":"F","size":14,"face":"Times-Roman"},{"op":"c","grad":"none","color":"#000000"},{"op":"T","pt":[188,301.8],"align":"c","width":232.87,"text":"cpsc410_ctrl_alt_elite/src/ast/LOAD.java"}],"fixedsize":"true","height":"0.5","label":"\\N","pos":"188,306","width":"0.19444","contributors":["Ceylin","Cyrielle","Ben","q6y0b"]},{"_gvid":6,"name":"cpsc410_ctrl_alt_elite/src/ast/PHOTOS.java","_draw_":[{"op":"c","grad":"none","color":"#000000"},{"op":"e","rect":[143,90,7,18]}],"_ldraw_":[{"op":"F","size":14,"face":"Times-Roman"},{"op":"c","grad":"none","color":"#000000"},{"op":"T","pt":[143,85.8],"align":"c","width":248.19,"text":"cpsc410_ctrl_alt_elite/src/ast/PHOTOS.java"}],"fixedsize":"true","height":"0.5","label":"\\N","pos":"143,90","width":"0.19444","contributors":["Cyrielle","Ceylin"]},{"_gvid":7,"name":"cpsc410_ctrl_alt_elite/src/ast/PROGRAM.java","_draw_":[{"op":"c","grad":"none","color":"#000000"},{"op":"e","rect":[85,306,7,18]}],"_ldraw_":[{"op":"F","size":14,"face":"Times-Roman"},{"op":"c","grad":"none","color":"#000000"},{"op":"T","pt":[85,301.8],"align":"c","width":263.22,"text":"cpsc410_ctrl_alt_elite/src/ast/PROGRAM.java"}],"fixedsize":"true","height":"0.5","label":"\\N","pos":"85,306","width":"0.19444","contributors":["Cyrielle","Ceylin","Ben","q6y0b"]},{"_gvid":8,"name":"cpsc410_ctrl_alt_elite/src/ast/SAVE.java","_draw_":[{"op":"c","grad":"none","color":"#000000"},{"op":"e","rect":[188,378,7,18]}],"_ldraw_":[{"op":"F","size":14,"face":"Times-Roman"},{"op":"c","grad":"none","color":"#000000"},{"op":"T","pt":[188,373.8],"align":"c","width":228.74,"text":"cpsc410_ctrl_alt_elite/src/ast/SAVE.java"}],"fixedsize":"true","height":"0.5","label":"\\N","pos":"188,378","width":"0.19444","contributors":["Ben","q6y0b","Ceylin","Cyrielle"]},{"_gvid":9,"name":"cpsc410_ctrl_alt_elite/src/ast/STATEMENT.java","_draw_":[{"op":"c","grad":"none","color":"#000000"},{"op":"e","rect":[138,234,7,18]}],"_ldraw_":[{"op":"F","size":14,"face":"Times-Roman"},{"op":"c","grad":"none","color":"#000000"},{"op":"T","pt":[138,229.8],"align":"c","width":273.5,"text":"cpsc410_ctrl_alt_elite/src/ast/STATEMENT.java"}],"fixedsize":"true","height":"0.5","label":"\\N","pos":"138,234","width":"0.19444","contributors":["Cyrielle"]},{"_gvid":10,"name":"cpsc410_ctrl_alt_elite/src/filter/Blur.java","_draw_":[{"op":"c","grad":"none","color":"#000000"},{"op":"e","rect":[85,378,7,18]}],"_ldraw_":[{"op":"F","size":14,"face":"Times-Roman"},{"op":"c","grad":"none","color":"#000000"},{"op":"T","pt":[85,373.8],"align":"c","width":229,"text":"cpsc410_ctrl_alt_elite/src/filter/Blur.java"}],"fixedsize":"true","height":"0.5","label":"\\N","pos":"85,378","width":"0.19444","contributors":["Cyrielle","Ben","Ceylin"]},{"_gvid":11,"name":"cpsc410_ctrl_alt_elite/src/filter/Brighten.java","_draw_":[{"op":"c","grad":"none","color":"#000000"},{"op":"e","rect":[155,738,7,18]}],"_ldraw_":[{"op":"F","size":14,"face":"Times-Roman"},{"op":"c","grad":"none","color":"#000000"},{"op":"T","pt":[155,733.8],"align":"c","width":253.87,"text":"cpsc410_ctrl_alt_elite/src/filter/Brighten.java"}],"fixedsize":"true","height":"0.5","label":"\\N","pos":"155,738","width":"0.19444","contributors":["Ben"]},{"_gvid":12,"name":"cpsc410_ctrl_alt_elite/src/filter/Contrast.java","_draw_":[{"op":"c","grad":"none","color":"#000000"},{"op":"e","rect":[203,810,7,18]}],"_ldraw_":[{"op":"F","size":14,"face":"Times-Roman"},{"op":"c","grad":"none","color":"#000000"},{"op":"T","pt":[203,805.8],"align":"c","width":252.31,"text":"cpsc410_ctrl_alt_elite/src/filter/Contrast.java"}],"fixedsize":"true","height":"0.5","label":"\\N","pos":"203,810","width":"0.19444","contributors":[]},{"_gvid":13,"name":"cpsc410_ctrl_alt_elite/src/filter/Darken.java","_draw_":[{"op":"c","grad":"none","color":"#000000"},{"op":"e","rect":[185,18,7,18]}],"_ldraw_":[{"op":"F","size":14,"face":"Times-Roman"},{"op":"c","grad":"none","color":"#000000"},{"op":"T","pt":[185,13.8],"align":"c","width":246.07,"text":"cpsc410_ctrl_alt_elite/src/filter/Darken.java"}],"fixedsize":"true","height":"0.5","label":"\\N","pos":"185,18","width":"0.19444","contributors":["Ben"]},{"_gvid":14,"name":"cpsc410_ctrl_alt_elite/src/filter/Filter.java","_draw_":[{"op":"c","grad":"none","color":"#000000"},{"op":"e","rect":[253,306,7,18]}],"_ldraw_":[{"op":"F","size":14,"face":"Times-Roman"},{"op":"c","grad":"none","color":"#000000"},{"op":"T","pt":[253,301.8],"align":"c","width":234.44,"text":"cpsc410_ctrl_alt_elite/src/filter/Filter.java"}],"fixedsize":"true","height":"0.5","label":"\\N","pos":"253,306","width":"0.19444","contributors":["Cyrielle","Ben","Ceylin"]},{"_gvid":15,"name":"cpsc410_ctrl_alt_elite/src/filter/FilterTest.java","_draw_":[{"op":"c","grad":"none","color":"#000000"},{"op":"e","rect":[188,738,7,18]}],"_ldraw_":[{"op":"F","size":14,"face":"Times-Roman"},{"op":"c","grad":"none","color":"#000000"},{"op":"T","pt":[188,733.8],"align":"c","width":258.33,"text":"cpsc410_ctrl_alt_elite/src/filter/FilterTest.java"}],"fixedsize":"true","height":"0.5","label":"\\N","pos":"188,738","width":"0.19444","contributors":["Ben","Cyrielle"]},{"_gvid":16,"name":"cpsc410_ctrl_alt_elite/src/filter/Invert.java","_draw_":[{"op":"c","grad":"none","color":"#000000"},{"op":"e","rect":[30,594,7,18]}],"_ldraw_":[{"op":"F","size":14,"face":"Times-Roman"},{"op":"c","grad":"none","color":"#000000"},{"op":"T","pt":[30,589.8],"align":"c","width":238.3,"text":"cpsc410_ctrl_alt_elite/src/filter/Invert.java"}],"fixedsize":"true","height":"0.5","label":"\\N","pos":"30,594","width":"0.19444","contributors":["Ben"]},{"_gvid":17,"name":"cpsc410_ctrl_alt_elite/src/filter/Sharpen.java","_draw_":[{"op":"c","grad":"none","color":"#000000"},{"op":"e","rect":[201,90,7,18]}],"_ldraw_":[{"op":"F","size":14,"face":"Times-Roman"},{"op":"c","grad":"none","color":"#000000"},{"op":"T","pt":[201,85.8],"align":"c","width":250.75,"text":"cpsc410_ctrl_alt_elite/src/filter/Sharpen.java"}],"fixedsize":"true","height":"0.5","label":"\\N","pos":"201,90","width":"0.19444","contributors":["Ben","Cyrielle"]},{"_gvid":18,"name":"cpsc410_ctrl_alt_elite/src/libs/FilterNotFoundException.java","_draw_":[{"op":"c","grad":"none","color":"#000000"},{"op":"e","rect":[41,450,7,18]}],"_ldraw_":[{"op":"F","size":14,"face":"Times-Roman"},{"op":"c","grad":"none","color":"#000000"},{"op":"T","pt":[41,445.8],"align":"c","width":342.54,"text":"cpsc410_ctrl_alt_elite/src/libs/FilterNotFoundException.java"}],"fixedsize":"true","height":"0.5","label":"\\N","pos":"41,450","width":"0.19444","contributors":["Ben"]},{"_gvid":19,"name":"cpsc410_ctrl_alt_elite/src/libs/NameCheckException.java","_draw_":[{"op":"c","grad":"none","color":"#000000"},{"op":"e","rect":[85,594,7,18]}],"_ldraw_":[{"op":"F","size":14,"face":"Times-Roman"},{"op":"c","grad":"none","color":"#000000"},{"op":"T","pt":[85,589.8],"align":"c","width":324.61,"text":"cpsc410_ctrl_alt_elite/src/libs/NameCheckException.java"}],"fixedsize":"true","height":"0.5","label":"\\N","pos":"85,594","width":"0.19444","contributors":["Ceylin","Ben"]},{"_gvid":20,"name":"cpsc410_ctrl_alt_elite/src/libs/NoFileFoundException.java","_draw_":[{"op":"c","grad":"none","color":"#000000"},{"op":"e","rect":[156,162,7,18]}],"_ldraw_":[{"op":"F","size":14,"face":"Times-Roman"},{"op":"c","grad":"none","color":"#000000"},{"op":"T","pt":[156,157.8],"align":"c","width":330.09,"text":"cpsc410_ctrl_alt_elite/src/libs/NoFileFoundException.java"}],"fixedsize":"true","height":"0.5","label":"\\N","pos":"156,162","width":"0.19444","contributors":["Ceylin","Ben"]},{"_gvid":21,"name":"cpsc410_ctrl_alt_elite/src/libs/Node.java","_draw_":[{"op":"c","grad":"none","color":"#000000"},{"op":"e","rect":[188,162,7,18]}],"_ldraw_":[{"op":"F","size":14,"face":"Times-Roman"},{"op":"c","grad":"none","color":"#000000"},{"op":"T","pt":[188,157.8],"align":"c","width":228.98,"text":"cpsc410_ctrl_alt_elite/src/libs/Node.java"}],"fixedsize":"true","height":"0.5","label":"\\N","pos":"188,162","width":"0.19444","contributors":["Cyrielle","Ceylin"]},{"_gvid":22,"name":"cpsc410_ctrl_alt_elite/src/libs/Tokenizer.java","_draw_":[{"op":"c","grad":"none","color":"#000000"},{"op":"e","rect":[217,18,7,18]}],"_ldraw_":[{"op":"F","size":14,"face":"Times-Roman"},{"op":"c","grad":"none","color":"#000000"},{"op":"T","pt":[217,13.8],"align":"c","width":253.66,"text":"cpsc410_ctrl_alt_elite/src/libs/Tokenizer.java"}],"fixedsize":"true","height":"0.5","label":"\\N","pos":"217,18","width":"0.19444","contributors":["Cyrielle"]},{"_gvid":23,"name":"cpsc410_ctrl_alt_elite/src/mainrun/Main.java","_draw_":[{"op":"c","grad":"none","color":"#000000"},{"op":"e","rect":[188,234,7,18]}],"_ldraw_":[{"op":"F","size":14,"face":"Times-Roman"},{"op":"c","grad":"none","color":"#000000"},{"op":"T","pt":[188,229.8],"align":"c","width":254.64,"text":"cpsc410_ctrl_alt_elite/src/mainrun/Main.java"}],"fixedsize":"true","height":"0.5","label":"\\N","pos":"188,234","width":"0.19444","contributors":["Cyrielle","Ceylin","Ben","q6y0b"]},{"_gvid":24,"name":"cpsc410_ctrl_alt_elite/src/mainrun/OpenCvTest.java","_draw_":[{"op":"c","grad":"none","color":"#000000"},{"op":"e","rect":[7,450,7,18]}],"_ldraw_":[{"op":"F","size":14,"face":"Times-Roman"},{"op":"c","grad":"none","color":"#000000"},{"op":"T","pt":[7,445.8],"align":"c","width":294.88,"text":"cpsc410_ctrl_alt_elite/src/mainrun/OpenCvTest.java"}],"fixedsize":"true","height":"0.5","label":"\\N","pos":"7,450","width":"0.19444","contributors":["Ben","Cyrielle"]}],"edges":[{"_gvid":0,"tail":0,"head":11,"_draw_":[{"op":"S","style":"setlinewidth(1.5)"},{"op":"c","grad":"none","color":"#6eceb2"},{"op":"b","points":[[168.67,792.69],[168.67,769.71],[168.67,732],[168.67,732],[168.67,732],[167.98,732],[167.98,732]]}],"_hdraw_":[{"op":"S","style":"setlinewidth(1.5)"},{"op":"S","style":"solid"},{"op":"c","grad":"none","color":"#6eceb2"},{"op":"C","grad":"none","color":"#6eceb2"},{"op":"P","points":[[171.83,728.5],[161.83,732],[171.83,735.5]]}],"color":"#6eceb2","penwidth":"1.5","pos":"e,161.83,732 168.67,792.69 168.67,769.71 168.67,732 168.67,732 168.67,732 167.98,732 167.98,732"},{"_gvid":1,"tail":0,"head":15,"_draw_":[{"op":"S","style":"setlinewidth(1.5)"},{"op":"c","grad":"none","color":"#6eceb2"},{"op":"b","points":[[173.33,793],[173.33,773.45],[173.33,744],[173.33,744],[173.33,744],[174.14,744],[174.14,744]]}],"_hdraw_":[{"op":"S","style":"setlinewidth(1.5)"},{"op":"S","style":"solid"},{"op":"c","grad":"none","color":"#6eceb2"},{"op":"C","grad":"none","color":"#6eceb2"},{"op":"P","points":[[171.35,747.5],[181.35,744],[171.35,740.5]]}],"color":"#6eceb2","penwidth":"1.5","pos":"e,181.35,744 173.33,793 173.33,773.45 173.33,744 173.33,744 173.33,744 174.14,744 174.14,744"},{"_gvid":2,"tail":1,"head":4,"_draw_":[{"op":"S","style":"setlinewidth(1.5)"},{"op":"c","grad":"none","color":"#00a3e0"},{"op":"b","points":[[47.66,528],[59.64,528],[83.6,528],[83.6,528],[83.6,528],[83.6,477.7],[83.6,477.7]]}],"_hdraw_":[{"op":"S","style":"setlinewidth(1.5)"},{"op":"S","style":"solid"},{"op":"c","grad":"none","color":"#00a3e0"},{"op":"C","grad":"none","color":"#00a3e0"},{"op":"P","points":[[87.1,477.7],[83.6,467.7],[80.1,477.7]]}],"color":"#00a3e0","penwidth":"1.5","pos":"e,83.6,467.7 47.656,528 59.638,528 83.6,528 83.6,528 83.6,528 83.6,477.7 83.6,477.7"},{"_gvid":3,"tail":1,"head":4,"_draw_":[{"op":"S","style":"setlinewidth(1.5)"},{"op":"c","grad":"none","color":"#10069f"},{"op":"b","points":[[47.93,516],[59.34,516],[80.8,516],[80.8,516],[80.8,516],[80.8,474.65],[80.8,474.65]]}],"_hdraw_":[{"op":"S","style":"setlinewidth(1.5)"},{"op":"S","style":"solid"},{"op":"c","grad":"none","color":"#10069f"},{"op":"C","grad":"none","color":"#10069f"},{"op":"P","points":[[84.3,474.65],[80.8,464.65],[77.3,474.65]]}],"color":"#10069f","penwidth":"1.5","pos":"e,80.8,464.65 47.933,516 59.336,516 80.8,516 80.8,516 80.8,516 80.8,474.65 80.8,474.65"},{"_gvid":4,"tail":1,"head":18,"_draw_":[{"op":"S","style":"setlinewidth(1.5)"},{"op":"c","grad":"none","color":"#6eceb2"},{"op":"b","points":[[41,503.83],[41,503.83],[41,478.41],[41,478.41]]}],"_hdraw_":[{"op":"S","style":"setlinewidth(1.5)"},{"op":"S","style":"solid"},{"op":"c","grad":"none","color":"#6eceb2"},{"op":"C","grad":"none","color":"#6eceb2"},{"op":"P","points":[[44.5,478.41],[41,468.41],[37.5,478.41]]}],"color":"#6eceb2","penwidth":"1.5","pos":"e,41,468.41 41,503.83 41,503.83 41,478.41 41,478.41"},{"_gvid":5,"tail":1,"head":19,"_draw_":[{"op":"S","style":"setlinewidth(1.5)"},{"op":"c","grad":"none","color":"#000000"},{"op":"b","points":[[40.67,540.09],[40.67,563.13],[40.67,600],[40.67,600],[40.67,600],[68.07,600],[68.07,600]]}],"_hdraw_":[{"op":"S","style":"setlinewidth(1.5)"},{"op":"S","style":"solid"},{"op":"c","grad":"none","color":"#000000"},{"op":"C","grad":"none","color":"#000000"},{"op":"P","points":[[68.07,603.5],[78.07,600],[68.07,596.5]]}],"color":"#000000","penwidth":"1.5","pos":"e,78.073,600 40.667,540.09 40.667,563.13 40.667,600 40.667,600 40.667,600 68.073,600 68.073,600"},{"_gvid":6,"tail":1,"head":24,"_draw_":[{"op":"S","style":"setlinewidth(1.5)"},{"op":"c","grad":"none","color":"#10069f"},{"op":"b","points":[[33.79,522],[23.81,522],[7,522],[7,522],[7,522],[7,478.17],[7,478.17]]}],"_hdraw_":[{"op":"S","style":"setlinewidth(1.5)"},{"op":"S","style":"solid"},{"op":"c","grad":"none","color":"#10069f"},{"op":"C","grad":"none","color":"#10069f"},{"op":"P","points":[[10.5,478.17],[7,468.17],[3.5,478.17]]}],"color":"#10069f","penwidth":"1.5","pos":"e,7,468.17 33.789,522 23.809,522 7,522 7,522 7,522 7,478.17 7,478.17"},{"_gvid":7,"tail":3,"head":8,"_draw_":[{"op":"S","style":"setlinewidth(1.5)"},{"op":"c","grad":"none","color":"#6eceb2"},{"op":"b","points":[[191.5,650.11],[191.5,650.11],[191.5,403.85],[191.5,403.85]]}],"_hdraw_":[{"op":"S","style":"setlinewidth(1.5)"},{"op":"S","style":"solid"},{"op":"c","grad":"none","color":"#6eceb2"},{"op":"C","grad":"none","color":"#6eceb2"},{"op":"P","points":[[195,403.85],[191.5,393.85],[188,403.85]]}],"color":"#6eceb2","penwidth":"1.5","pos":"e,191.5,393.85 191.5,650.11 191.5,650.11 191.5,403.85 191.5,403.85"},{"_gvid":8,"tail":3,"head":8,"_draw_":[{"op":"S","style":"setlinewidth(1.5)"},{"op":"c","grad":"none","color":"#10069f"},{"op":"b","points":[[193.25,653.99],[193.25,653.99],[193.25,400.06],[193.25,400.06]]}],"_hdraw_":[{"op":"S","style":"setlinewidth(1.5)"},{"op":"S","style":"solid"},{"op":"c","grad":"none","color":"#10069f"},{"op":"C","grad":"none","color":"#10069f"},{"op":"P","points":[[196.75,400.06],[193.25,390.06],[189.75,400.06]]}],"color":"#10069f","penwidth":"1.5","pos":"e,193.25,390.06 193.25,653.99 193.25,653.99 193.25,400.06 193.25,400.06"},{"_gvid":9,"tail":3,"head":8,"_draw_":[{"op":"S","style":"setlinewidth(1.5)"},{"op":"c","grad":"none","color":"#000000"},{"op":"b","points":[[189.75,648.42],[189.75,648.42],[189.75,405.72],[189.75,405.72]]}],"_hdraw_":[{"op":"S","style":"setlinewidth(1.5)"},{"op":"S","style":"solid"},{"op":"c","grad":"none","color":"#000000"},{"op":"C","grad":"none","color":"#000000"},{"op":"P","points":[[193.25,405.72],[189.75,395.72],[186.25,405.72]]}],"color":"#000000","penwidth":"1.5","pos":"e,189.75,395.72 189.75,648.42 189.75,648.42 189.75,405.72 189.75,405.72"},{"_gvid":10,"tail":3,"head":15,"_draw_":[{"op":"S","style":"setlinewidth(1.5)"},{"op":"c","grad":"none","color":"#10069f"},{"op":"b","points":[[190.33,683.06],[190.33,683.06],[190.33,710.56],[190.33,710.56]]}],"_hdraw_":[{"op":"S","style":"setlinewidth(1.5)"},{"op":"S","style":"solid"},{"op":"c","grad":"none","color":"#10069f"},{"op":"C","grad":"none","color":"#10069f"},{"op":"P","points":[[186.83,710.56],[190.33,720.56],[193.83,710.56]]}],"color":"#10069f","penwidth":"1.5","pos":"e,190.33,720.56 190.33,683.06 190.33,683.06 190.33,710.56 190.33,710.56"},{"_gvid":11,"tail":3,"head":19,"_draw_":[{"op":"S","style":"setlinewidth(1.5)"},{"op":"c","grad":"none","color":"#6eceb2"},{"op":"b","points":[[186.25,648.3],[186.25,625.29],[186.25,588],[186.25,588],[186.25,588],[101.64,588],[101.64,588]]}],"_hdraw_":[{"op":"S","style":"setlinewidth(1.5)"},{"op":"S","style":"solid"},{"op":"c","grad":"none","color":"#6eceb2"},{"op":"C","grad":"none","color":"#6eceb2"},{"op":"P","points":[[101.64,584.5],[91.64,588],[101.64,591.5]]}],"color":"#6eceb2","penwidth":"1.5","pos":"e,91.643,588 186.25,648.3 186.25,625.29 186.25,588 186.25,588 186.25,588 101.64,588 101.64,588"},{"_gvid":12,"tail":4,"head":3,"_draw_":[{"op":"S","style":"setlinewidth(1.5)"},{"op":"c","grad":"none","color":"#10069f"},{"op":"b","points":[[91.76,456],[114.67,456],[188,456],[188,456],[188,456],[188,637.73],[188,637.73]]}],"_hdraw_":[{"op":"S","style":"setlinewidth(1.5)"},{"op":"S","style":"solid"},{"op":"c","grad":"none","color":"#10069f"},{"op":"C","grad":"none","color":"#10069f"},{"op":"P","points":[[184.5,637.73],[188,647.73],[191.5,637.73]]}],"color":"#10069f","penwidth":"1.5","pos":"e,188,647.73 91.758,456 114.67,456 188,456 188,456 188,456 188,637.73 188,637.73"},{"_gvid":13,"tail":4,"head":7,"_draw_":[{"op":"S","style":"setlinewidth(1.5)"},{"op":"c","grad":"none","color":"#00a3e0"},{"op":"b","points":[[77.58,450],[72.13,450],[65.67,450],[65.67,450],[65.67,450],[65.67,312],[65.67,312],[65.67,312],[68.02,312],[68.02,312]]}],"_hdraw_":[{"op":"S","style":"setlinewidth(1.5)"},{"op":"S","style":"solid"},{"op":"c","grad":"none","color":"#00a3e0"},{"op":"C","grad":"none","color":"#00a3e0"},{"op":"P","points":[[68.02,315.5],[78.02,312],[68.02,308.5]]}],"color":"#00a3e0","penwidth":"1.5","pos":"e,78.02,312 77.581,450 72.128,450 65.667,450 65.667,450 65.667,450 65.667,312 65.667,312 65.667,312 68.02,312 68.02,312"},{"_gvid":14,"tail":4,"head":8,"_draw_":[{"op":"S","style":"setlinewidth(1.5)"},{"op":"c","grad":"none","color":"#00a3e0"},{"op":"b","points":[[91.72,444],[113.8,444],[182.75,444],[182.75,444],[182.75,444],[182.75,400.11],[182.75,400.11]]}],"_hdraw_":[{"op":"S","style":"setlinewidth(1.5)"},{"op":"S","style":"solid"},{"op":"c","grad":"none","color":"#00a3e0"},{"op":"C","grad":"none","color":"#00a3e0"},{"op":"P","points":[[186.25,400.11],[182.75,390.11],[179.25,400.11]]}],"color":"#00a3e0","penwidth":"1.5","pos":"e,182.75,390.11 91.719,444 113.8,444 182.75,444 182.75,444 182.75,444 182.75,400.11 182.75,400.11"},{"_gvid":15,"tail":4,"head":10,"_draw_":[{"op":"S","style":"setlinewidth(1.5)"},{"op":"c","grad":"none","color":"#6eceb2"},{"op":"b","points":[[81.5,434.38],[81.5,434.38],[81.5,403.59],[81.5,403.59]]}],"_hdraw_":[{"op":"S","style":"setlinewidth(1.5)"},{"op":"S","style":"solid"},{"op":"c","grad":"none","color":"#6eceb2"},{"op":"C","grad":"none","color":"#6eceb2"},{"op":"P","points":[[85,403.59],[81.5,393.59],[78,403.59]]}],"color":"#6eceb2","penwidth":"1.5","pos":"e,81.5,393.59 81.5,434.38 81.5,434.38 81.5,403.59 81.5,403.59"},{"_gvid":16,"tail":4,"head":10,"_draw_":[{"op":"S","style":"setlinewidth(1.5)"},{"op":"c","grad":"none","color":"#10069f"},{"op":"b","points":[[85,431.83],[85,431.83],[85,406.41],[85,406.41]]}],"_hdraw_":[{"op":"S","style":"setlinewidth(1.5)"},{"op":"S","style":"solid"},{"op":"c","grad":"none","color":"#10069f"},{"op":"C","grad":"none","color":"#10069f"},{"op":"P","points":[[88.5,406.41],[85,396.41],[81.5,406.41]]}],"color":"#10069f","penwidth":"1.5","pos":"e,85,396.41 85,431.83 85,431.83 85,406.41 85,406.41"},{"_gvid":17,"tail":4,"head":10,"_draw_":[{"op":"S","style":"setlinewidth(1.5)"},{"op":"c","grad":"none","color":"#000000"},{"op":"b","points":[[88.5,434.38],[88.5,434.38],[88.5,403.59],[88.5,403.59]]}],"_hdraw_":[{"op":"S","style":"setlinewidth(1.5)"},{"op":"S","style":"solid"},{"op":"c","grad":"none","color":"#000000"},{"op":"C","grad":"none","color":"#000000"},{"op":"P","points":[[92,403.59],[88.5,393.59],[85,403.59]]}],"color":"#000000","penwidth":"1.5","pos":"e,88.5,393.59 88.5,434.38 88.5,434.38 88.5,403.59 88.5,403.59"},{"_gvid":18,"tail":5,"head":23,"_draw_":[{"op":"S","style":"setlinewidth(1.5)"},{"op":"c","grad":"none","color":"#6eceb2"},{"op":"b","points":[[183.8,291.43],[183.8,291.43],[183.8,258.55],[183.8,258.55]]}],"_hdraw_":[{"op":"S","style":"setlinewidth(1.5)"},{"op":"S","style":"solid"},{"op":"c","grad":"none","color":"#6eceb2"},{"op":"C","grad":"none","color":"#6eceb2"},{"op":"P","points":[[187.3,258.55],[183.8,248.55],[180.3,258.55]]}],"color":"#6eceb2","penwidth":"1.5","pos":"e,183.8,248.55 183.8,291.43 183.8,291.43 183.8,258.55 183.8,258.55"},{"_gvid":19,"tail":5,"head":23,"_draw_":[{"op":"S","style":"setlinewidth(1.5)"},{"op":"c","grad":"none","color":"#00a3e0"},{"op":"b","points":[[192.2,291.43],[192.2,291.43],[192.2,258.55],[192.2,258.55]]}],"_hdraw_":[{"op":"S","style":"setlinewidth(1.5)"},{"op":"S","style":"solid"},{"op":"c","grad":"none","color":"#00a3e0"},{"op":"C","grad":"none","color":"#00a3e0"},{"op":"P","points":[[195.7,258.55],[192.2,248.55],[188.7,258.55]]}],"color":"#00a3e0","penwidth":"1.5","pos":"e,192.2,248.55 192.2,291.43 192.2,291.43 192.2,258.55 192.2,258.55"},{"_gvid":20,"tail":5,"head":23,"_draw_":[{"op":"S","style":"setlinewidth(1.5)"},{"op":"c","grad":"none","color":"#10069f"},{"op":"b","points":[[189.4,288.2],[189.4,288.2],[189.4,261.84],[189.4,261.84]]}],"_hdraw_":[{"op":"S","style":"setlinewidth(1.5)"},{"op":"S","style":"solid"},{"op":"c","grad":"none","color":"#10069f"},{"op":"C","grad":"none","color":"#10069f"},{"op":"P","points":[[192.9,261.84],[189.4,251.84],[185.9,261.84]]}],"color":"#10069f","penwidth":"1.5","pos":"e,189.4,251.84 189.4,288.2 189.4,288.2 189.4,261.84 189.4,261.84"},{"_gvid":21,"tail":5,"head":23,"_draw_":[{"op":"S","style":"setlinewidth(1.5)"},{"op":"c","grad":"none","color":"#000000"},{"op":"b","points":[[186.6,288.2],[186.6,288.2],[186.6,261.84],[186.6,261.84]]}],"_hdraw_":[{"op":"S","style":"setlinewidth(1.5)"},{"op":"S","style":"solid"},{"op":"c","grad":"none","color":"#000000"},{"op":"C","grad":"none","color":"#000000"},{"op":"P","points":[[190.1,261.84],[186.6,251.84],[183.1,261.84]]}],"color":"#000000","penwidth":"1.5","pos":"e,186.6,251.84 186.6,288.2 186.6,288.2 186.6,261.84 186.6,261.84"},{"_gvid":22,"tail":7,"head":2,"_draw_":[{"op":"S","style":"setlinewidth(1.5)"},{"op":"c","grad":"none","color":"#000000"},{"op":"b","points":[[78.35,300],[74.47,300],[70.33,300],[70.33,300],[70.33,300],[70.33,261],[70.33,261]]}],"_hdraw_":[{"op":"S","style":"setlinewidth(1.5)"},{"op":"S","style":"solid"},{"op":"c","grad":"none","color":"#000000"},{"op":"C","grad":"none","color":"#000000"},{"op":"P","points":[[73.83,261],[70.33,251],[66.83,261]]}],"color":"#000000","penwidth":"1.5","pos":"e,70.333,251 78.353,300 74.473,300 70.333,300 70.333,300 70.333,300 70.333,261 70.333,261"},{"_gvid":23,"tail":7,"head":6,"_draw_":[{"op":"S","style":"setlinewidth(1.5)"},{"op":"c","grad":"none","color":"#10069f"},{"op":"b","points":[[85,287.96],[85,236.04],[85,90],[85,90],[85,90],[125.89,90],[125.89,90]]}],"_hdraw_":[{"op":"S","style":"setlinewidth(1.5)"},{"op":"S","style":"solid"},{"op":"c","grad":"none","color":"#10069f"},{"op":"C","grad":"none","color":"#10069f"},{"op":"P","points":[[125.89,93.5],[135.89,90],[125.89,86.5]]}],"color":"#10069f","penwidth":"1.5","pos":"e,135.89,90 85,287.96 85,236.04 85,90 85,90 85,90 125.89,90 125.89,90"},{"_gvid":24,"tail":7,"head":9,"_draw_":[{"op":"S","style":"setlinewidth(1.5)"},{"op":"c","grad":"none","color":"#10069f"},{"op":"b","points":[[92.37,306],[106.93,306],[138,306],[138,306],[138,306],[138,262.17],[138,262.17]]}],"_hdraw_":[{"op":"S","style":"setlinewidth(1.5)"},{"op":"S","style":"solid"},{"op":"c","grad":"none","color":"#10069f"},{"op":"C","grad":"none","color":"#10069f"},{"op":"P","points":[[141.5,262.17],[138,252.17],[134.5,262.17]]}],"color":"#10069f","penwidth":"1.5","pos":"e,138,252.17 92.369,306 106.93,306 138,306 138,306 138,306 138,262.17 138,262.17"},{"_gvid":25,"tail":8,"head":5,"_draw_":[{"op":"S","style":"setlinewidth(1.5)"},{"op":"c","grad":"none","color":"#6eceb2"},{"op":"b","points":[[192.2,363.43],[192.2,363.43],[192.2,330.55],[192.2,330.55]]}],"_hdraw_":[{"op":"S","style":"setlinewidth(1.5)"},{"op":"S","style":"solid"},{"op":"c","grad":"none","color":"#6eceb2"},{"op":"C","grad":"none","color":"#6eceb2"},{"op":"P","points":[[195.7,330.55],[192.2,320.55],[188.7,330.55]]}],"color":"#6eceb2","penwidth":"1.5","pos":"e,192.2,320.55 192.2,363.43 192.2,363.43 192.2,330.55 192.2,330.55"},{"_gvid":26,"tail":8,"head":5,"_draw_":[{"op":"S","style":"setlinewidth(1.5)"},{"op":"c","grad":"none","color":"#00a3e0"},{"op":"b","points":[[189.4,360.2],[189.4,360.2],[189.4,333.84],[189.4,333.84]]}],"_hdraw_":[{"op":"S","style":"setlinewidth(1.5)"},{"op":"S","style":"solid"},{"op":"c","grad":"none","color":"#00a3e0"},{"op":"C","grad":"none","color":"#00a3e0"},{"op":"P","points":[[192.9,333.84],[189.4,323.84],[185.9,333.84]]}],"color":"#00a3e0","penwidth":"1.5","pos":"e,189.4,323.84 189.4,360.2 189.4,360.2 189.4,333.84 189.4,333.84"},{"_gvid":27,"tail":8,"head":5,"_draw_":[{"op":"S","style":"setlinewidth(1.5)"},{"op":"c","grad":"none","color":"#10069f"},{"op":"b","points":[[186.6,360.2],[186.6,360.2],[186.6,333.84],[186.6,333.84]]}],"_hdraw_":[{"op":"S","style":"setlinewidth(1.5)"},{"op":"S","style":"solid"},{"op":"c","grad":"none","color":"#10069f"},{"op":"C","grad":"none","color":"#10069f"},{"op":"P","points":[[190.1,333.84],[186.6,323.84],[183.1,333.84]]}],"color":"#10069f","penwidth":"1.5","pos":"e,186.6,323.84 186.6,360.2 186.6,360.2 186.6,333.84 186.6,333.84"},{"_gvid":28,"tail":8,"head":5,"_draw_":[{"op":"S","style":"setlinewidth(1.5)"},{"op":"c","grad":"none","color":"#000000"},{"op":"b","points":[[183.8,363.43],[183.8,363.43],[183.8,330.55],[183.8,330.55]]}],"_hdraw_":[{"op":"S","style":"setlinewidth(1.5)"},{"op":"S","style":"solid"},{"op":"c","grad":"none","color":"#000000"},{"op":"C","grad":"none","color":"#000000"},{"op":"P","points":[[187.3,330.55],[183.8,320.55],[180.3,330.55]]}],"color":"#000000","penwidth":"1.5","pos":"e,183.8,320.55 183.8,363.43 183.8,363.43 183.8,330.55 183.8,330.55"},{"_gvid":29,"tail":8,"head":14,"_draw_":[{"op":"S","style":"setlinewidth(1.5)"},{"op":"c","grad":"none","color":"#000000"},{"op":"b","points":[[195.05,378],[211.21,378],[249.5,378],[249.5,378],[249.5,378],[249.5,331.62],[249.5,331.62]]}],"_hdraw_":[{"op":"S","style":"setlinewidth(1.5)"},{"op":"S","style":"solid"},{"op":"c","grad":"none","color":"#000000"},{"op":"C","grad":"none","color":"#000000"},{"op":"P","points":[[253,331.62],[249.5,321.62],[246,331.62]]}],"color":"#000000","penwidth":"1.5","pos":"e,249.5,321.62 195.05,378 211.21,378 249.5,378 249.5,378 249.5,378 249.5,331.62 249.5,331.62"},{"_gvid":30,"tail":10,"head":7,"_draw_":[{"op":"S","style":"setlinewidth(1.5)"},{"op":"c","grad":"none","color":"#6eceb2"},{"op":"b","points":[[88.5,362.38],[88.5,362.38],[88.5,331.59],[88.5,331.59]]}],"_hdraw_":[{"op":"S","style":"setlinewidth(1.5)"},{"op":"S","style":"solid"},{"op":"c","grad":"none","color":"#6eceb2"},{"op":"C","grad":"none","color":"#6eceb2"},{"op":"P","points":[[92,331.59],[88.5,321.59],[85,331.59]]}],"color":"#6eceb2","penwidth":"1.5","pos":"e,88.5,321.59 88.5,362.38 88.5,362.38 88.5,331.59 88.5,331.59"},{"_gvid":31,"tail":10,"head":7,"_draw_":[{"op":"S","style":"setlinewidth(1.5)"},{"op":"c","grad":"none","color":"#10069f"},{"op":"b","points":[[85,359.83],[85,359.83],[85,334.41],[85,334.41]]}],"_hdraw_":[{"op":"S","style":"setlinewidth(1.5)"},{"op":"S","style":"solid"},{"op":"c","grad":"none","color":"#10069f"},{"op":"C","grad":"none","color":"#10069f"},{"op":"P","points":[[88.5,334.41],[85,324.41],[81.5,334.41]]}],"color":"#10069f","penwidth":"1.5","pos":"e,85,324.41 85,359.83 85,359.83 85,334.41 85,334.41"},{"_gvid":32,"tail":10,"head":7,"_draw_":[{"op":"S","style":"setlinewidth(1.5)"},{"op":"c","grad":"none","color":"#000000"},{"op":"b","points":[[81.5,362.38],[81.5,362.38],[81.5,331.59],[81.5,331.59]]}],"_hdraw_":[{"op":"S","style":"setlinewidth(1.5)"},{"op":"S","style":"solid"},{"op":"c","grad":"none","color":"#000000"},{"op":"C","grad":"none","color":"#000000"},{"op":"P","points":[[85,331.59],[81.5,321.59],[78,331.59]]}],"color":"#000000","penwidth":"1.5","pos":"e,81.5,321.59 81.5,362.38 81.5,362.38 81.5,331.59 81.5,331.59"},{"_gvid":33,"tail":11,"head":16,"_draw_":[{"op":"S","style":"setlinewidth(1.5)"},{"op":"c","grad":"none","color":"#6eceb2"},{"op":"b","points":[[147.92,738],[121.48,738],[30,738],[30,738],[30,738],[30,622.24],[30,622.24]]}],"_hdraw_":[{"op":"S","style":"setlinewidth(1.5)"},{"op":"S","style":"solid"},{"op":"c","grad":"none","color":"#6eceb2"},{"op":"C","grad":"none","color":"#6eceb2"},{"op":"P","points":[[33.5,622.24],[30,612.24],[26.5,622.24]]}],"color":"#6eceb2","penwidth":"1.5","pos":"e,30,612.24 147.92,738 121.48,738 30,738 30,738 30,738 30,622.24 30,622.24"},{"_gvid":34,"tail":15,"head":3,"_draw_":[{"op":"S","style":"setlinewidth(1.5)"},{"op":"c","grad":"none","color":"#6eceb2"},{"op":"b","points":[[185.67,720.94],[185.67,720.94],[185.67,693.44],[185.67,693.44]]}],"_hdraw_":[{"op":"S","style":"setlinewidth(1.5)"},{"op":"S","style":"solid"},{"op":"c","grad":"none","color":"#6eceb2"},{"op":"C","grad":"none","color":"#6eceb2"},{"op":"P","points":[[189.17,693.44],[185.67,683.44],[182.17,693.44]]}],"color":"#6eceb2","penwidth":"1.5","pos":"e,185.67,683.44 185.67,720.94 185.67,720.94 185.67,693.44 185.67,693.44"},{"_gvid":35,"tail":15,"head":14,"_draw_":[{"op":"S","style":"setlinewidth(1.5)"},{"op":"c","grad":"none","color":"#6eceb2"},{"op":"b","points":[[194.96,732],[211.72,732],[253,732],[253,732],[253,732],[253,334.03],[253,334.03]]}],"_hdraw_":[{"op":"S","style":"setlinewidth(1.5)"},{"op":"S","style":"solid"},{"op":"c","grad":"none","color":"#6eceb2"},{"op":"C","grad":"none","color":"#6eceb2"},{"op":"P","points":[[256.5,334.03],[253,324.03],[249.5,334.03]]}],"color":"#6eceb2","penwidth":"1.5","pos":"e,253,324.03 194.96,732 211.72,732 253,732 253,732 253,732 253,334.03 253,334.03"},{"_gvid":36,"tail":15,"head":14,"_draw_":[{"op":"S","style":"setlinewidth(1.5)"},{"op":"c","grad":"none","color":"#10069f"},{"op":"b","points":[[194.82,744],[212.14,744],[256.5,744],[256.5,744],[256.5,744],[256.5,331.59],[256.5,331.59]]}],"_hdraw_":[{"op":"S","style":"setlinewidth(1.5)"},{"op":"S","style":"solid"},{"op":"c","grad":"none","color":"#10069f"},{"op":"C","grad":"none","color":"#10069f"},{"op":"P","points":[[260,331.59],[256.5,321.59],[253,331.59]]}],"color":"#10069f","penwidth":"1.5","pos":"e,256.5,321.59 194.82,744 212.14,744 256.5,744 256.5,744 256.5,744 256.5,331.59 256.5,331.59"},{"_gvid":37,"tail":16,"head":24,"_draw_":[{"op":"S","style":"setlinewidth(1.5)"},{"op":"c","grad":"none","color":"#6eceb2"},{"op":"b","points":[[28.5,576.34],[28.5,537.89],[28.5,450],[28.5,450],[28.5,450],[24.28,450],[24.28,450]]}],"_hdraw_":[{"op":"S","style":"setlinewidth(1.5)"},{"op":"S","style":"solid"},{"op":"c","grad":"none","color":"#6eceb2"},{"op":"C","grad":"none","color":"#6eceb2"},{"op":"P","points":[[24.28,446.5],[14.28,450],[24.28,453.5]]}],"color":"#6eceb2","penwidth":"1.5","pos":"e,14.279,450 28.5,576.34 28.5,537.89 28.5,450 28.5,450 28.5,450 24.279,450 24.279,450"},{"_gvid":38,"tail":17,"head":13,"_draw_":[{"op":"S","style":"setlinewidth(1.5)"},{"op":"c","grad":"none","color":"#6eceb2"},{"op":"b","points":[[194.09,96],[190.36,96],[186.5,96],[186.5,96],[186.5,96],[186.5,45.7],[186.5,45.7]]}],"_hdraw_":[{"op":"S","style":"setlinewidth(1.5)"},{"op":"S","style":"solid"},{"op":"c","grad":"none","color":"#6eceb2"},{"op":"C","grad":"none","color":"#6eceb2"},{"op":"P","points":[[190,45.7],[186.5,35.7],[183,45.7]]}],"color":"#6eceb2","penwidth":"1.5","pos":"e,186.5,35.699 194.09,96 190.36,96 186.5,96 186.5,96 186.5,96 186.5,45.699 186.5,45.699"},{"_gvid":39,"tail":17,"head":22,"_draw_":[{"op":"S","style":"setlinewidth(1.5)"},{"op":"c","grad":"none","color":"#10069f"},{"op":"b","points":[[201,71.83],[201,50.5],[201,18],[201,18],[201,18],[201.87,18],[201.87,18]]}],"_hdraw_":[{"op":"S","style":"setlinewidth(1.5)"},{"op":"S","style":"solid"},{"op":"c","grad":"none","color":"#10069f"},{"op":"C","grad":"none","color":"#10069f"},{"op":"P","points":[[199.75,21.5],[209.75,18],[199.75,14.5]]}],"color":"#10069f","penwidth":"1.5","pos":"e,209.75,18 201,71.831 201,50.502 201,18 201,18 201,18 201.87,18 201.87,18"},{"_gvid":40,"tail":19,"head":1,"_draw_":[{"op":"S","style":"setlinewidth(1.5)"},{"op":"c","grad":"none","color":"#6eceb2"},{"op":"b","points":[[78.28,588],[66.73,588],[44.33,588],[44.33,588],[44.33,588],[44.33,547.98],[44.33,547.98]]}],"_hdraw_":[{"op":"S","style":"setlinewidth(1.5)"},{"op":"S","style":"solid"},{"op":"c","grad":"none","color":"#6eceb2"},{"op":"C","grad":"none","color":"#6eceb2"},{"op":"P","points":[[47.83,547.98],[44.33,537.98],[40.83,547.98]]}],"color":"#6eceb2","penwidth":"1.5","pos":"e,44.333,537.98 78.285,588 66.734,588 44.333,588 44.333,588 44.333,588 44.333,547.98 44.333,547.98"},{"_gvid":41,"tail":19,"head":3,"_draw_":[{"op":"S","style":"setlinewidth(1.5)"},{"op":"c","grad":"none","color":"#000000"},{"op":"b","points":[[91.84,600],[114.32,600],[184.5,600],[184.5,600],[184.5,600],[184.5,640.36],[184.5,640.36]]}],"_hdraw_":[{"op":"S","style":"setlinewidth(1.5)"},{"op":"S","style":"solid"},{"op":"c","grad":"none","color":"#000000"},{"op":"C","grad":"none","color":"#000000"},{"op":"P","points":[[181,640.36],[184.5,650.36],[188,640.36]]}],"color":"#000000","penwidth":"1.5","pos":"e,184.5,650.36 91.839,600 114.32,600 184.5,600 184.5,600 184.5,600 184.5,640.36 184.5,640.36"},{"_gvid":42,"tail":19,"head":4,"_draw_":[{"op":"S","style":"setlinewidth(1.5)"},{"op":"c","grad":"none","color":"#6eceb2"},{"op":"b","points":[[86.4,576.34],[86.4,576.34],[86.4,477.8],[86.4,477.8]]}],"_hdraw_":[{"op":"S","style":"setlinewidth(1.5)"},{"op":"S","style":"solid"},{"op":"c","grad":"none","color":"#6eceb2"},{"op":"C","grad":"none","color":"#6eceb2"},{"op":"P","points":[[89.9,477.8],[86.4,467.8],[82.9,477.8]]}],"color":"#6eceb2","penwidth":"1.5","pos":"e,86.4,467.8 86.4,576.34 86.4,576.34 86.4,477.8 86.4,477.8"},{"_gvid":43,"tail":19,"head":4,"_draw_":[{"op":"S","style":"setlinewidth(1.5)"},{"op":"c","grad":"none","color":"#000000"},{"op":"b","points":[[89.2,579.4],[89.2,579.4],[89.2,474.64],[89.2,474.64]]}],"_hdraw_":[{"op":"S","style":"setlinewidth(1.5)"},{"op":"S","style":"solid"},{"op":"c","grad":"none","color":"#000000"},{"op":"C","grad":"none","color":"#000000"},{"op":"P","points":[[92.7,474.64],[89.2,464.64],[85.7,474.64]]}],"color":"#000000","penwidth":"1.5","pos":"e,89.2,464.64 89.2,579.4 89.2,579.4 89.2,474.64 89.2,474.64"},{"_gvid":44,"tail":20,"head":6,"_draw_":[{"op":"S","style":"setlinewidth(1.5)"},{"op":"c","grad":"none","color":"#000000"},{"op":"b","points":[[156.5,143.91],[156.5,120.87],[156.5,84],[156.5,84],[156.5,84],[155.82,84],[155.82,84]]}],"_hdraw_":[{"op":"S","style":"setlinewidth(1.5)"},{"op":"S","style":"solid"},{"op":"c","grad":"none","color":"#000000"},{"op":"C","grad":"none","color":"#000000"},{"op":"P","points":[[159.75,80.5],[149.75,84],[159.75,87.5]]}],"color":"#000000","penwidth":"1.5","pos":"e,149.75,84 156.5,143.91 156.5,120.87 156.5,84 156.5,84 156.5,84 155.82,84 155.82,84"},{"_gvid":45,"tail":21,"head":17,"_draw_":[{"op":"S","style":"setlinewidth(1.5)"},{"op":"c","grad":"none","color":"#10069f"},{"op":"b","points":[[195.12,162],[197.7,162],[200,162],[200,162],[200,162],[200,118.17],[200,118.17]]}],"_hdraw_":[{"op":"S","style":"setlinewidth(1.5)"},{"op":"S","style":"solid"},{"op":"c","grad":"none","color":"#10069f"},{"op":"C","grad":"none","color":"#10069f"},{"op":"P","points":[[203.5,118.17],[200,108.17],[196.5,118.17]]}],"color":"#10069f","penwidth":"1.5","pos":"e,200,108.17 195.12,162 197.7,162 200,162 200,162 200,162 200,118.17 200,118.17"},{"_gvid":46,"tail":23,"head":17,"_draw_":[{"op":"S","style":"setlinewidth(1.5)"},{"op":"c","grad":"none","color":"#6eceb2"},{"op":"b","points":[[195.25,234],[199.48,234],[204,234],[204,234],[204,234],[204,116.52],[204,116.52]]}],"_hdraw_":[{"op":"S","style":"setlinewidth(1.5)"},{"op":"S","style":"solid"},{"op":"c","grad":"none","color":"#6eceb2"},{"op":"C","grad":"none","color":"#6eceb2"},{"op":"P","points":[[207.5,116.52],[204,106.52],[200.5,116.52]]}],"color":"#6eceb2","penwidth":"1.5","pos":"e,204,106.52 195.25,234 199.48,234 204,234 204,234 204,234 204,116.52 204,116.52"},{"_gvid":47,"tail":23,"head":20,"_draw_":[{"op":"S","style":"setlinewidth(1.5)"},{"op":"c","grad":"none","color":"#6eceb2"},{"op":"b","points":[[181.27,228],[172.33,228],[157.67,228],[157.67,228],[157.67,228],[157.67,189.69],[157.67,189.69]]}],"_hdraw_":[{"op":"S","style":"setlinewidth(1.5)"},{"op":"S","style":"solid"},{"op":"c","grad":"none","color":"#6eceb2"},{"op":"C","grad":"none","color":"#6eceb2"},{"op":"P","points":[[161.17,189.69],[157.67,179.69],[154.17,189.69]]}],"color":"#6eceb2","penwidth":"1.5","pos":"e,157.67,179.69 181.27,228 172.33,228 157.67,228 157.67,228 157.67,228 157.67,189.69 157.67,189.69"},{"_gvid":48,"tail":23,"head":20,"_draw_":[{"op":"S","style":"setlinewidth(1.5)"},{"op":"c","grad":"none","color":"#000000"},{"op":"b","points":[[181.32,240],[171.24,240],[153.33,240],[153.33,240],[153.33,240],[153.33,188.92],[153.33,188.92]]}],"_hdraw_":[{"op":"S","style":"setlinewidth(1.5)"},{"op":"S","style":"solid"},{"op":"c","grad":"none","color":"#000000"},{"op":"C","grad":"none","color":"#000000"},{"op":"P","points":[[156.83,188.92],[153.33,178.92],[149.83,188.92]]}],"color":"#000000","penwidth":"1.5","pos":"e,153.33,178.92 181.32,240 171.24,240 153.33,240 153.33,240 153.33,240 153.33,188.92 153.33,188.92"},{"_gvid":49,"tail":23,"head":21,"_draw_":[{"op":"S","style":"setlinewidth(1.5)"},{"op":"c","grad":"none","color":"#10069f"},{"op":"b","points":[[190.33,216.94],[190.33,216.94],[190.33,189.44],[190.33,189.44]]}],"_hdraw_":[{"op":"S","style":"setlinewidth(1.5)"},{"op":"S","style":"solid"},{"op":"c","grad":"none","color":"#10069f"},{"op":"C","grad":"none","color":"#10069f"},{"op":"P","points":[[193.83,189.44],[190.33,179.44],[186.83,189.44]]}],"color":"#10069f","penwidth":"1.5","pos":"e,190.33,179.44 190.33,216.94 190.33,216.94 190.33,189.44 190.33,189.44"},{"_gvid":50,"tail":23,"head":21,"_draw_":[{"op":"S","style":"setlinewidth(1.5)"},{"op":"c","grad":"none","color":"#000000"},{"op":"b","points":[[185.67,216.94],[185.67,216.94],[185.67,189.44],[185.67,189.44]]}],"_hdraw_":[{"op":"S","style":"setlinewidth(1.5)"},{"op":"S","style":"solid"},{"op":"c","grad":"none","color":"#000000"},{"op":"C","grad":"none","color":"#000000"},{"op":"P","points":[[189.17,189.44],[185.67,179.44],[182.17,189.44]]}],"color":"#000000","penwidth":"1.5","pos":"e,185.67,179.44 185.67,216.94 185.67,216.94 185.67,189.44 185.67,189.44"}]}